{"url":"https://twly.herokuapp.com/api/bill/135/","billid":1044,"proposalid":14041,"law":"政治獻金法","title":"政治獻金法第十八條條文修正草案\u0007","motivation":"本院委員趙天麟、許智傑、李昆澤、林世嘉、蘇震清、田秋堇、蕭美琴等22人，有鑑於現行政治獻金法雖有規定捐贈人捐贈上限，惟對於近年來為節省社會成本，降低選舉支出，往往合併多次選舉種類於同一時間舉辦，如2009年合併縣市長、議員及鄉鎮市長、2010年合併直轄市長、議員及里長選舉及2012年合併立委及總統選舉等等，中央選舉委員會並計畫於2014年合併直轄市長、直轄市議員、縣市長、縣市議員、鄉鎮市長、鄉鎮市民代表及村里長等，如合併計算捐贈人捐款上限，將扼殺捐贈人對不同選舉種類擬參選人之支持，爰提案修正「政治獻金法第十八條條文」，將捐贈人對於不同選舉種類之捐贈金額應分開計算。是否有當，敬請公決。","description":"一、現行政治獻金法規定捐贈人對於擬參選人每年捐贈總額個人不得超過新臺幣二十萬元，營利事業不得超過新臺幣二百萬元及人民團體不得超過新臺幣一百萬元，雖有規定捐贈人捐贈上限，惟對於同時舉行之不同選舉種類卻無分開計算金額，導致捐贈人對於擬參選人的支持權利被剝奪。\n\n二、近年來為節省社會成本，降低選舉支出，往往合併多次選舉種類於同一時間舉辦，如2009年合併縣市長、議員及鄉鎮市長、2010年合併直轄市長、議員及里長選舉及2012年合併立委及總統選舉等等，中央選舉委員會並計畫於2014年合併直轄市長、直轄市議員、縣市長、縣市議員、鄉鎮市長、鄉鎮市民代表及村里長等，如合併計算捐贈人捐款上限，將導致捐贈人對不同選舉種類擬參選人之支持度被強烈分割。\n\n三、政治獻金法原提案立法之原始目的「為免造成不當利益輸送」，於是限制個人及營利事業捐款上限，然並未考慮到合併選舉種類後，如無分開計算捐贈額度，即壓縮到捐贈人對擬參選人之支持空間，提案修正「政治獻金法第十八條」，將捐贈人對於不同選舉種類之捐贈金額應分開計算。","date":null,"committee":"內政","sessionPrd":8,"proposer":["https://twly.herokuapp.com/api/legislator/59/","https://twly.herokuapp.com/api/legislator/82/","https://twly.herokuapp.com/api/legislator/13/","https://twly.herokuapp.com/api/legislator/96/","https://twly.herokuapp.com/api/legislator/18/","https://twly.herokuapp.com/api/legislator/70/","https://twly.herokuapp.com/api/legislator/57/"]}