{"url":"https://twly.herokuapp.com/api/bill/214/","billid":468,"proposalid":12990,"law":"就業保險法","title":"就業保險法增訂第二十二條之一條文草案\r\u0007","motivation":"本院委員蔣乃辛、鄭汝芬、吳育仁、丁守中等34人，有鑑於現行「就業保險法」中，並未明文規範被保險人因可歸責於保險人遲延給付而受損害的救濟作為，有損勞工之給付權益。為維護勞工權益，參酌司法院釋字第六百八十三號解釋意旨，以及公教人員保險法第二十二條規定，爰增訂「就業保險法第二十二條之一」。是否有當，敬請公決。","description":"一、對於可歸責於保險人的遲延給付，法律並未明文規範，有損勞工之給付權益，有必要進行檢討，並研擬修法。\n\n二、基於憲法保護勞工原則，本席等參酌司法院釋字第六百八十三號解釋意旨，以及公教人員保險法第二十二條規定，爰新增第二十二條之一條文，以維護勞工。\n\n三、修法重點：新增第二十二條之一，依本法發給之保險給付，經保險人核定後，應在十天內給付。如逾期給付可歸責於保險人者，其逾期部分應加給利息。","date":null,"committee":"社會福利及衛生環境","sessionPrd":8,"proposer":["https://twly.herokuapp.com/api/legislator/51/","https://twly.herokuapp.com/api/legislator/12/","https://twly.herokuapp.com/api/legislator/49/","https://twly.herokuapp.com/api/legislator/32/"]}